gubbins/__init__.py
gubbins/generate.py
gubbins/gubbins.py
gubbins/validate.py
gubbins-0.0.3.dist-info/LICENSE
gubbins-0.0.3.dist-info/METADATA
gubbins-0.0.3.dist-info/WHEEL
gubbins-0.0.3.dist-info/entry_points.txt
gubbins-0.0.3.dist-info/top_level.txt
gubbins-0.0.3.dist-info/RECORD
