Metadata-Version: 2.1
Name: gubbins
Version: 0.0.3
Summary: Serial number generator/validator
Home-page: https://github.com/ArgosyLabs/gubbins
Author: Derrick Lyndon Pallas
Author-email: derrick@argosylabs.com
License: MIT
Keywords: serial generator validator
Platform: UNKNOWN
Classifier: Development Status :: 3 - Alpha
Classifier: Programming Language :: Python :: 3 :: Only
Classifier: Topic :: Software Development :: Libraries :: Python Modules
Classifier: Topic :: Utilities
Classifier: Topic :: Security
Classifier: License :: OSI Approved :: MIT License
Requires-Dist: more-itertools
Requires-Dist: anybase32
Requires-Dist: pynumparser
